django_admin_filter/__init__.py
django_admin_filter/admin.py
django_admin_filter/apps.py
django_admin_filter/filters.py
django_admin_filter/filterset.py
django_admin_filter/forms.py
django_admin_filter/models.py
django_admin_filter/settings.py
django_admin_filter/urls.py
django_admin_filter/views.py
django_admin_filter/locale/de/LC_MESSAGES/django.mo
django_admin_filter/locale/de/LC_MESSAGES/django.po
django_admin_filter/locale/es/LC_MESSAGES/django.mo
django_admin_filter/locale/es/LC_MESSAGES/django.po
django_admin_filter/locale/fr/LC_MESSAGES/django.mo
django_admin_filter/locale/fr/LC_MESSAGES/django.po
django_admin_filter/locale/it/LC_MESSAGES/django.mo
django_admin_filter/locale/it/LC_MESSAGES/django.po
django_admin_filter/migrations/0001_initial.py
django_admin_filter/migrations/0002_filterquery_for_everyone.py
django_admin_filter/migrations/0003_auto_20210125_0905.py
django_admin_filter/migrations/0004_auto_20210129_1058.py
django_admin_filter/migrations/0005_auto_20210308_2052.py
django_admin_filter/migrations/__init__.py
django_admin_filter/templates/django_admin_filter/custom_filter.html
django_admin_filter/templates/django_admin_filter/filter_query.html
django_admin_filter/templatetags/__init__.py
django_admin_filter/templatetags/django_admin_filter.py
django_admin_filter-0.7.dist-info/LICENCE
django_admin_filter-0.7.dist-info/METADATA
django_admin_filter-0.7.dist-info/WHEEL
django_admin_filter-0.7.dist-info/top_level.txt
django_admin_filter-0.7.dist-info/zip-safe
django_admin_filter-0.7.dist-info/RECORD
